Metadata-Version: 1.0
Name: group06
Version: 0.0.6
Summary: 第六小组的第三方库
Home-page: https://github.com/harukazeeee/group5
Author: five
Author-email: 854412413@qq.com
License: UNKNOWN
Platform: UNKNOWN
